{
  "title": "Absolute Hypnosis in Another World",
  "description": "A hypnotic life story in another world of a man armed with hypnosis ability, status window, dog logic and self-rationalization!",
  "artist": "Grilled Mero",
  "author": "OneDollar",
  "cover": "https://fmcdn.mangahere.com/store/manga/43985/ocover.jpg?token=e2356029e47e5fd4a8867ff3bedab9bebfe4d11c&ttl=1783288800&v=1681112943",
  "chapters": {
    "02": {
      "title": "",
      "last_updated": "1783205947",
      "groups": {
        "": "/proxy/api/imgchest/chapter/9ryd9xvkd7k"
      }
    },
    "04": {
      "title": "",
      "last_updated": "1783205948",
      "groups": {
        "": "/proxy/api/imgchest/chapter/ljyqpvnwe72"
      }
    },
    "03": {
      "title": "",
      "last_updated": "1783205948",
      "groups": {
        "": "/proxy/api/imgchest/chapter/vj4jp9rl548"
      }
    },
    "06": {
      "title": "",
      "last_updated": "1783205957",
      "groups": {
        "": "/proxy/api/imgchest/chapter/n87wplwa34x"
      }
    },
    "01": {
      "title": "",
      "last_updated": "1783205966",
      "groups": {
        "": "/proxy/api/imgchest/chapter/wl7lp9eq6yx"
      }
    },
    "05": {
      "title": "",
      "last_updated": "1783205968",
      "groups": {
        "": "/proxy/api/imgchest/chapter/ej7mp9gdq7d"
      }
    },
    "07": {
      "title": "",
      "last_updated": "1783205975",
      "groups": {
        "": "/proxy/api/imgchest/chapter/lqyeka9xxyd"
      }
    },
    "10": {
      "title": "",
      "last_updated": "1783205982",
      "groups": {
        "": "/proxy/api/imgchest/chapter/bp45v3awxy5"
      }
    },
    "08": {
      "title": "",
      "last_updated": "1783205983",
      "groups": {
        "": "/proxy/api/imgchest/chapter/qe4g9eonoyj"
      }
    },
    "09": {
      "title": "",
      "last_updated": "1783205984",
      "groups": {
        "": "/proxy/api/imgchest/chapter/xny8n3bgpyb"
      }
    },
    "11": {
      "title": "",
      "last_updated": "1783205991",
      "groups": {
        "": "/proxy/api/imgchest/chapter/agyvp2m3wy8"
      }
    },
    "14": {
      "title": "",
      "last_updated": "1783205996",
      "groups": {
        "": "/proxy/api/imgchest/chapter/9249nvo8vyn"
      }
    },
    "12": {
      "title": "",
      "last_updated": "1783206002",
      "groups": {
        "": "/proxy/api/imgchest/chapter/m9yxpjzem4q"
      }
    },
    "15": {
      "title": "",
      "last_updated": "1783206004",
      "groups": {
        "": "/proxy/api/imgchest/chapter/ne7b958eky5"
      }
    },
    "13": {
      "title": "",
      "last_updated": "1783206005",
      "groups": {
        "": "/proxy/api/imgchest/chapter/9p4non5pw7n"
      }
    },
    "16": {
      "title": "",
      "last_updated": "1783206009",
      "groups": {
        "": "/proxy/api/imgchest/chapter/dl7ppvxl87o"
      }
    },
    "19": {
      "title": "",
      "last_updated": "1783206014",
      "groups": {
        "": "/proxy/api/imgchest/chapter/5xy25dwrnyl"
      }
    },
    "17": {
      "title": "",
      "last_updated": "1783206015",
      "groups": {
        "": "/proxy/api/imgchest/chapter/md7op962ayp"
      }
    },
    "20": {
      "title": "",
      "last_updated": "1783206017",
      "groups": {
        "": "/proxy/api/imgchest/chapter/vj4jp9rx548"
      }
    },
    "18": {
      "title": "",
      "last_updated": "1783206018",
      "groups": {
        "": "/proxy/api/imgchest/chapter/na7kpo39k48"
      }
    },
    "21": {
      "title": "",
      "last_updated": "1783206023",
      "groups": {
        "": "/proxy/api/imgchest/chapter/ljyqpvnje72"
      }
    },
    "22": {
      "title": "",
      "last_updated": "1783206024",
      "groups": {
        "": "/proxy/api/imgchest/chapter/9ryd9xvgd7k"
      }
    },
    "23": {
      "title": "",
      "last_updated": "1783206027",
      "groups": {
        "": "/proxy/api/imgchest/chapter/6eyrkvpqk7p"
      }
    },
    "24": {
      "title": "",
      "last_updated": "1783206027",
      "groups": {
        "": "/proxy/api/imgchest/chapter/pg73arzmvyr"
      }
    },
    "25": {
      "title": "",
      "last_updated": "1783206032",
      "groups": {
        "": "/proxy/api/imgchest/chapter/lqyeka98xyd"
      }
    },
    "26": {
      "title": "",
      "last_updated": "1783206035",
      "groups": {
        "": "/proxy/api/imgchest/chapter/qb4z2dagg4j"
      }
    },
    "27": {
      "title": "",
      "last_updated": "1783206036",
      "groups": {
        "": "/proxy/api/imgchest/chapter/qe4g9eoaoyj"
      }
    },
    "28": {
      "title": "",
      "last_updated": "1783206042",
      "groups": {
        "": "/proxy/api/imgchest/chapter/xny8n3bbpyb"
      }
    },
    "29": {
      "title": "",
      "last_updated": "1783206043",
      "groups": {
        "": "/proxy/api/imgchest/chapter/bp45v3aaxy5"
      }
    },
    "30": {
      "title": "",
      "last_updated": "1783206043",
      "groups": {
        "": "/proxy/api/imgchest/chapter/o24a93zzgyl"
      }
    },
    "33": {
      "title": "",
      "last_updated": "1783206049",
      "groups": {
        "": "/proxy/api/imgchest/chapter/agyvp2mmwy8"
      }
    },
    "32": {
      "title": "",
      "last_updated": "1783206050",
      "groups": {
        "": "/proxy/api/imgchest/chapter/m9yxpjzzm4q"
      }
    },
    "34": {
      "title": "",
      "last_updated": "1783206051",
      "groups": {
        "": "/proxy/api/imgchest/chapter/9249nvoovyn"
      }
    },
    "31": {
      "title": "",
      "last_updated": "1783206051",
      "groups": {
        "": "/proxy/api/imgchest/chapter/a846npvvgyx"
      }
    },
    "35": {
      "title": "",
      "last_updated": "1783206055",
      "groups": {
        "": "/proxy/api/imgchest/chapter/9p4non55w7n"
      }
    },
    "36": {
      "title": "",
      "last_updated": "1783206056",
      "groups": {
        "": "/proxy/api/imgchest/chapter/ne7b9588ky5"
      }
    },
    "37": {
      "title": "",
      "last_updated": "1783206059",
      "groups": {
        "": "/proxy/api/imgchest/chapter/dl7ppvxx87o"
      }
    },
    "38": {
      "title": "",
      "last_updated": "1783206059",
      "groups": {
        "": "/proxy/api/imgchest/chapter/md7op966ayp"
      }
    },
    "40": {
      "title": "",
      "last_updated": "1783206064",
      "groups": {
        "": "/proxy/api/imgchest/chapter/5xy25dwwnyl"
      }
    },
    "39": {
      "title": "",
      "last_updated": "1783206066",
      "groups": {
        "": "/proxy/api/imgchest/chapter/wl7lp9ee6yx"
      }
    },
    "42": {
      "title": "",
      "last_updated": "1783206066",
      "groups": {
        "": "/proxy/api/imgchest/chapter/ljyqpvnne72"
      }
    },
    "41": {
      "title": "",
      "last_updated": "1783206067",
      "groups": {
        "": "/proxy/api/imgchest/chapter/vj4jp9rr548"
      }
    },
    "43": {
      "title": "",
      "last_updated": "1783206073",
      "groups": {
        "": "/proxy/api/imgchest/chapter/9ryd9xvvd7k"
      }
    },
    "46": {
      "title": "",
      "last_updated": "1783206075",
      "groups": {
        "": "/proxy/api/imgchest/chapter/pg73arzzvyr"
      }
    },
    "44": {
      "title": "",
      "last_updated": "1783206076",
      "groups": {
        "": "/proxy/api/imgchest/chapter/ej7mp9ggq7d"
      }
    },
    "45": {
      "title": "",
      "last_updated": "1783206076",
      "groups": {
        "": "/proxy/api/imgchest/chapter/n87wplww34x"
      }
    },
    "47": {
      "title": "",
      "last_updated": "1783206082",
      "groups": {
        "": "/proxy/api/imgchest/chapter/lqyeka99xyd"
      }
    },
    "48": {
      "title": "",
      "last_updated": "1783206084",
      "groups": {
        "": "/proxy/api/imgchest/chapter/qb4z2daag4j"
      }
    },
    "50": {
      "title": "",
      "last_updated": "1783206087",
      "groups": {
        "": "/proxy/api/imgchest/chapter/xny8nvpppyb"
      }
    },
    "49": {
      "title": "",
      "last_updated": "1783206090",
      "groups": {
        "": "/proxy/api/imgchest/chapter/bp45vpkkxy5"
      }
    },
    "51": {
      "title": "",
      "last_updated": "1783206091",
      "groups": {
        "": "/proxy/api/imgchest/chapter/o24a9qxxgyl"
      }
    },
    "52": {
      "title": "",
      "last_updated": "1783206093",
      "groups": {
        "": "/proxy/api/imgchest/chapter/a846nwrrgyx"
      }
    },
    "53": {
      "title": "",
      "last_updated": "1783206096",
      "groups": {
        "": "/proxy/api/imgchest/chapter/agyvpqzzwy8"
      }
    },
    "54": {
      "title": "",
      "last_updated": "1783206100",
      "groups": {
        "": "/proxy/api/imgchest/chapter/9249nwxxvyn"
      }
    },
    "55": {
      "title": "",
      "last_updated": "1783206101",
      "groups": {
        "": "/proxy/api/imgchest/chapter/9p4nowggw7n"
      }
    },
    "56": {
      "title": "",
      "last_updated": "1783206101",
      "groups": {
        "": "/proxy/api/imgchest/chapter/ne7b9dggky5"
      }
    },
    "57": {
      "title": "",
      "last_updated": "1783206108",
      "groups": {
        "": "/proxy/api/imgchest/chapter/md7opwzzayp"
      }
    },
    "58": {
      "title": "",
      "last_updated": "1783206110",
      "groups": {
        "": "/proxy/api/imgchest/chapter/na7kpmxxk48"
      }
    },
    "59": {
      "title": "",
      "last_updated": "1783206111",
      "groups": {
        "": "/proxy/api/imgchest/chapter/5xy25azznyl"
      }
    },
    "60": {
      "title": "",
      "last_updated": "1783206112",
      "groups": {
        "": "/proxy/api/imgchest/chapter/wl7lpgzz6yx"
      }
    },
    "62": {
      "title": "",
      "last_updated": "1783206117",
      "groups": {
        "": "/proxy/api/imgchest/chapter/9ryd9mlld7k"
      }
    },
    "63": {
      "title": "",
      "last_updated": "1783206119",
      "groups": {
        "": "/proxy/api/imgchest/chapter/6eyrk9rrk7p"
      }
    },
    "61": {
      "title": "",
      "last_updated": "1783206120",
      "groups": {
        "": "/proxy/api/imgchest/chapter/ljyqpxgge72"
      }
    },
    "65": {
      "title": "",
      "last_updated": "1783206128",
      "groups": {
        "": "/proxy/api/imgchest/chapter/pg73agkkvyr"
      }
    },
    "64": {
      "title": "",
      "last_updated": "1783206129",
      "groups": {
        "": "/proxy/api/imgchest/chapter/ej7mpwzzq7d"
      }
    },
    "66": {
      "title": "",
      "last_updated": "1783206132",
      "groups": {
        "": "/proxy/api/imgchest/chapter/lqyek2jjxyd"
      }
    },
    "67": {
      "title": "",
      "last_updated": "1783206136",
      "groups": {
        "": "/proxy/api/imgchest/chapter/qb4z2e66g4j"
      }
    },
    "68": {
      "title": "",
      "last_updated": "1783206146",
      "groups": {
        "": "/proxy/api/imgchest/chapter/bp45vpkxxy5"
      }
    },
    "69": {
      "title": "",
      "last_updated": "1783206146",
      "groups": {
        "": "/proxy/api/imgchest/chapter/xny8nvpxpyb"
      }
    },
    "71": {
      "title": "",
      "last_updated": "1783206149",
      "groups": {
        "": "/proxy/api/imgchest/chapter/a846nwragyx"
      }
    },
    "70": {
      "title": "",
      "last_updated": "1783206155",
      "groups": {
        "": "/proxy/api/imgchest/chapter/agyvpqzdwy8"
      }
    },
    "72": {
      "title": "",
      "last_updated": "1783206159",
      "groups": {
        "": "/proxy/api/imgchest/chapter/9249nwxzvyn"
      }
    },
    "73": {
      "title": "",
      "last_updated": "1783206159",
      "groups": {
        "": "/proxy/api/imgchest/chapter/m9yxprxkm4q"
      }
    },
    "74": {
      "title": "",
      "last_updated": "1783206160",
      "groups": {
        "": "/proxy/api/imgchest/chapter/9p4nowgew7n"
      }
    },
    "75": {
      "title": "",
      "last_updated": "1783206167",
      "groups": {
        "": "/proxy/api/imgchest/chapter/ne7b9dgwky5"
      }
    },
    "76": {
      "title": "",
      "last_updated": "1783206169",
      "groups": {
        "": "/proxy/api/imgchest/chapter/md7opwzgayp"
      }
    },
    "77": {
      "title": "",
      "last_updated": "1783206170",
      "groups": {
        "": "/proxy/api/imgchest/chapter/na7kpmxzk48"
      }
    },
    "78": {
      "title": "",
      "last_updated": "1783206171",
      "groups": {
        "": "/proxy/api/imgchest/chapter/5xy25azpnyl"
      }
    },
    "79": {
      "title": "",
      "last_updated": "1783206179",
      "groups": {
        "": "/proxy/api/imgchest/chapter/ljyqpxg9e72"
      }
    },
    "80": {
      "title": "",
      "last_updated": "1783206179",
      "groups": {
        "": "/proxy/api/imgchest/chapter/5xy25azpjyl"
      }
    },
    "81": {
      "title": "",
      "last_updated": "1783206180",
      "groups": {
        "": "/proxy/api/imgchest/chapter/wl7lpgzxpyx"
      }
    },
    "82": {
      "title": "",
      "last_updated": "1783206182",
      "groups": {
        "": "/proxy/api/imgchest/chapter/vj4jpkod248"
      }
    },
    "84": {
      "title": "",
      "last_updated": "1783206189",
      "groups": {
        "": "/proxy/api/imgchest/chapter/6eyrk9rge7p"
      }
    },
    "83": {
      "title": "",
      "last_updated": "1783206190",
      "groups": {
        "": "/proxy/api/imgchest/chapter/9ryd9ml5w7k"
      }
    },
    "85": {
      "title": "",
      "last_updated": "1783206191",
      "groups": {
        "": "/proxy/api/imgchest/chapter/ej7mpwzmb7d"
      }
    }
  }
}