{
  "title": "Not Friends",
  "description": "Véspera de Natal aos 21 anos. Geonwoo, que este ano está solteiro novamente e como sempre, não pensou muito na sua amiga de infância. “A sugestão da Haru é passar a véspera juntos”. “Você… se lembra de quando dissemos que deveríamos nos ajudar mutuamente se ainda estivéssemos solteiros quando tivéssemos 22 anos de idade? O pensamento da amiga parece diferente, na verdade, parece que… Alternative Titles: Blurred Lines | Not a Friend - What Do I Call Her As? | Not Friend's | Plus qu'amis | Не друзья | 不想當朋友 | 我們不是朋友 | 친구말고 |",
  "artist": "Saeltto",
  "author": "BaePero",
  "cover": "https://awshc.r2d2storage.com/oldcovers/2023/05/Not-a-friend-What-do-I-call-her-as.jpg",
  "chapters": {
    "04": {
      "title": "",
      "last_updated": "1783539708",
      "groups": {
        "XxTRUCOxX": "/proxy/api/imgchest/chapter/pg73al28zyr"
      }
    },
    "01": {
      "title": "",
      "last_updated": "1783539710",
      "groups": {
        "XxTRUCOxX": "/proxy/api/imgchest/chapter/ej7mp8j6b7d"
      }
    },
    "02": {
      "title": "",
      "last_updated": "1783539712",
      "groups": {
        "XxTRUCOxX": "/proxy/api/imgchest/chapter/6eyrkl36e7p"
      }
    },
    "03": {
      "title": "",
      "last_updated": "1783539713",
      "groups": {
        "XxTRUCOxX": "/proxy/api/imgchest/chapter/9ryd9r3ew7k"
      }
    },
    "05": {
      "title": "",
      "last_updated": "1783539722",
      "groups": {
        "XxTRUCOxX": "/proxy/api/imgchest/chapter/lqyekmww3yd"
      }
    },
    "06": {
      "title": "",
      "last_updated": "1783539725",
      "groups": {
        "XxTRUCOxX": "/proxy/api/imgchest/chapter/qb4z2nll34j"
      }
    },
    "07": {
      "title": "",
      "last_updated": "1783539737",
      "groups": {
        "XxTRUCOxX": "/proxy/api/imgchest/chapter/qe4g9wzzryj"
      }
    },
    "08": {
      "title": "",
      "last_updated": "1783539742",
      "groups": {
        "XxTRUCOxX": "/proxy/api/imgchest/chapter/xny8nmrroyb"
      }
    },
    "09": {
      "title": "",
      "last_updated": "1783539744",
      "groups": {
        "XxTRUCOxX": "/proxy/api/imgchest/chapter/bp45vqjj2y5"
      }
    },
    "10": {
      "title": "",
      "last_updated": "1783539747",
      "groups": {
        "XxTRUCOxX": "/proxy/api/imgchest/chapter/o24a9jdd3yl"
      }
    },
    "11": {
      "title": "",
      "last_updated": "1783539757",
      "groups": {
        "XxTRUCOxX": "/proxy/api/imgchest/chapter/9p4no8qqz7n"
      }
    },
    "12": {
      "title": "",
      "last_updated": "1783539764",
      "groups": {
        "XxTRUCOxX": "/proxy/api/imgchest/chapter/ne7b9qrrny5"
      }
    },
    "14": {
      "title": "",
      "last_updated": "1783539773",
      "groups": {
        "XxTRUCOxX": "/proxy/api/imgchest/chapter/md7op8dddyp"
      }
    },
    "13": {
      "title": "",
      "last_updated": "1783539774",
      "groups": {
        "XxTRUCOxX": "/proxy/api/imgchest/chapter/dl7pp8rr67o"
      }
    },
    "15": {
      "title": "",
      "last_updated": "1783539775",
      "groups": {
        "XxTRUCOxX": "/proxy/api/imgchest/chapter/na7kp822q48"
      }
    },
    "16": {
      "title": "",
      "last_updated": "1783539780",
      "groups": {
        "XxTRUCOxX": "/proxy/api/imgchest/chapter/5xy252xxjyl"
      }
    },
    "19": {
      "title": "",
      "last_updated": "1783539788",
      "groups": {
        "XxTRUCOxX": "/proxy/api/imgchest/chapter/9ryd9r33w7k"
      }
    },
    "17": {
      "title": "",
      "last_updated": "1783539788",
      "groups": {
        "XxTRUCOxX": "/proxy/api/imgchest/chapter/vj4jp855248"
      }
    },
    "18": {
      "title": "",
      "last_updated": "1783539793",
      "groups": {
        "XxTRUCOxX": "/proxy/api/imgchest/chapter/ljyqp2mmo72"
      }
    },
    "20": {
      "title": "",
      "last_updated": "1783539798",
      "groups": {
        "XxTRUCOxX": "/proxy/api/imgchest/chapter/ej7mp8jjb7d"
      }
    },
    "22": {
      "title": "",
      "last_updated": "1783539803",
      "groups": {
        "XxTRUCOxX": "/proxy/api/imgchest/chapter/n87wpm82z4x"
      }
    },
    "21": {
      "title": "",
      "last_updated": "1783539806",
      "groups": {
        "XxTRUCOxX": "/proxy/api/imgchest/chapter/pg73al22zyr"
      }
    },
    "23": {
      "title": "",
      "last_updated": "1783539813",
      "groups": {
        "XxTRUCOxX": "/proxy/api/imgchest/chapter/lqyekmwo3yd"
      }
    },
    "24": {
      "title": "",
      "last_updated": "1783539815",
      "groups": {
        "XxTRUCOxX": "/proxy/api/imgchest/chapter/qb4z2nlq34j"
      }
    },
    "25": {
      "title": "",
      "last_updated": "1783539824",
      "groups": {
        "XxTRUCOxX": "/proxy/api/imgchest/chapter/qe4g9wzkryj"
      }
    },
    "26": {
      "title": "",
      "last_updated": "1783539825",
      "groups": {
        "XxTRUCOxX": "/proxy/api/imgchest/chapter/xny8nmr8oyb"
      }
    },
    "27": {
      "title": "",
      "last_updated": "1783539831",
      "groups": {
        "XxTRUCOxX": "/proxy/api/imgchest/chapter/bp45vqje2y5"
      }
    },
    "28": {
      "title": "",
      "last_updated": "1783539834",
      "groups": {
        "XxTRUCOxX": "/proxy/api/imgchest/chapter/o24a9jdo3yl"
      }
    },
    "29": {
      "title": "",
      "last_updated": "1783539842",
      "groups": {
        "XxTRUCOxX": "/proxy/api/imgchest/chapter/m9yxp35l34q"
      }
    },
    "30": {
      "title": "",
      "last_updated": "1783539842",
      "groups": {
        "XxTRUCOxX": "/proxy/api/imgchest/chapter/9249n3m52yn"
      }
    },
    "31": {
      "title": "",
      "last_updated": "1783539848",
      "groups": {
        "XxTRUCOxX": "/proxy/api/imgchest/chapter/ne7b9qrony5"
      }
    },
    "32": {
      "title": "",
      "last_updated": "1783539852",
      "groups": {
        "XxTRUCOxX": "/proxy/api/imgchest/chapter/md7op8d3dyp"
      }
    },
    "33": {
      "title": "",
      "last_updated": "1783539857",
      "groups": {
        "XxTRUCOxX": "/proxy/api/imgchest/chapter/9ryd9r3ow7k"
      }
    },
    "34": {
      "title": "",
      "last_updated": "1783539859",
      "groups": {
        "XxTRUCOxX": "/proxy/api/imgchest/chapter/ljyqp2meo72"
      }
    },
    "35": {
      "title": "",
      "last_updated": "1783539867",
      "groups": {
        "XxTRUCOxX": "/proxy/api/imgchest/chapter/6eyrkl3ze7p"
      }
    },
    "36": {
      "title": "",
      "last_updated": "1783539869",
      "groups": {
        "XxTRUCOxX": "/proxy/api/imgchest/chapter/pg73al23zyr"
      }
    },
    "37": {
      "title": "",
      "last_updated": "1783539875",
      "groups": {
        "XxTRUCOxX": "/proxy/api/imgchest/chapter/lqyekmwr3yd"
      }
    },
    "38": {
      "title": "",
      "last_updated": "1783539878",
      "groups": {
        "XxTRUCOxX": "/proxy/api/imgchest/chapter/qb4z2nlb34j"
      }
    },
    "39": {
      "title": "",
      "last_updated": "1783539887",
      "groups": {
        "XxTRUCOxX": "/proxy/api/imgchest/chapter/qe4g9wz3ryj"
      }
    },
    "40": {
      "title": "",
      "last_updated": "1783539888",
      "groups": {
        "XxTRUCOxX": "/proxy/api/imgchest/chapter/xny8nmrwoyb"
      }
    },
    "41": {
      "title": "",
      "last_updated": "1783539893",
      "groups": {
        "XxTRUCOxX": "/proxy/api/imgchest/chapter/a846ndqmwyx"
      }
    },
    "42": {
      "title": "",
      "last_updated": "1783539901",
      "groups": {
        "XxTRUCOxX": "/proxy/api/imgchest/chapter/m9yxp35b34q"
      }
    },
    "45": {
      "title": "",
      "last_updated": "1783539903",
      "groups": {
        "XxTRUCOxX": "/proxy/api/imgchest/chapter/wl7lpol8pyx"
      }
    },
    "44": {
      "title": "",
      "last_updated": "1783539910",
      "groups": {
        "XxTRUCOxX": "/proxy/api/imgchest/chapter/md7op8dkdyp"
      }
    },
    "43": {
      "title": "",
      "last_updated": "1783539913",
      "groups": {
        "XxTRUCOxX": "/proxy/api/imgchest/chapter/dl7pp8rb67o"
      }
    },
    "47": {
      "title": "",
      "last_updated": "1783539922",
      "groups": {
        "XxTRUCOxX": "/proxy/api/imgchest/chapter/ej7mp8j5b7d"
      }
    },
    "46": {
      "title": "",
      "last_updated": "1783539923",
      "groups": {
        "XxTRUCOxX": "/proxy/api/imgchest/chapter/ljyqp2mbo72"
      }
    },
    "49": {
      "title": "",
      "last_updated": "1783539932",
      "groups": {
        "XxTRUCOxX": "/proxy/api/imgchest/chapter/qe4g9wz9ryj"
      }
    },
    "48": {
      "title": "",
      "last_updated": "1783539934",
      "groups": {
        "XxTRUCOxX": "/proxy/api/imgchest/chapter/lqyekmwk3yd"
      }
    },
    "51": {
      "title": "",
      "last_updated": "1783539938",
      "groups": {
        "XxTRUCOxX": "/proxy/api/imgchest/chapter/agyvprgp9y8"
      }
    },
    "50": {
      "title": "",
      "last_updated": "1783539938",
      "groups": {
        "XxTRUCOxX": "/proxy/api/imgchest/chapter/o24a9jd93yl"
      }
    },
    "52": {
      "title": "",
      "last_updated": "1783539950",
      "groups": {
        "XxTRUCOxX": "/proxy/api/imgchest/chapter/md7op8dpdyp"
      }
    },
    "54": {
      "title": "",
      "last_updated": "1783539956",
      "groups": {
        "XxTRUCOxX": "/proxy/api/imgchest/chapter/vj4jp85p248"
      }
    },
    "53": {
      "title": "",
      "last_updated": "1783539957",
      "groups": {
        "XxTRUCOxX": "/proxy/api/imgchest/chapter/5xy252x5jyl"
      }
    },
    "55": {
      "title": "",
      "last_updated": "1783539962",
      "groups": {
        "XxTRUCOxX": "/proxy/api/imgchest/chapter/ljyqp2mpo72"
      }
    },
    "56": {
      "title": "",
      "last_updated": "1783539965",
      "groups": {
        "XxTRUCOxX": "/proxy/api/imgchest/chapter/ej7mp8jqn7d"
      }
    },
    "57": {
      "title": "",
      "last_updated": "1783539976",
      "groups": {
        "XxTRUCOxX": "/proxy/api/imgchest/chapter/lqyekmw5qyd"
      }
    },
    "58": {
      "title": "",
      "last_updated": "1783539978",
      "groups": {
        "XxTRUCOxX": "/proxy/api/imgchest/chapter/qb4z2nlvd4j"
      }
    },
    "59": {
      "title": "",
      "last_updated": "1783539980",
      "groups": {
        "XxTRUCOxX": "/proxy/api/imgchest/chapter/qe4g9wz6jyj"
      }
    },
    "60": {
      "title": "",
      "last_updated": "1783539989",
      "groups": {
        "XxTRUCOxX": "/proxy/api/imgchest/chapter/xny8nmrk5yb"
      }
    }
  }
}