{
  "title": "Obscene Private Lesson",
  "description": "Jung-seop, no primeiro dia que começou a dar aulas particulares para a filha de uma amiga de sua mãe, ele rouba a calcinha que estava pendurada no banheiro porque não suportava a vontade de tocá-la. Ele tentou devolvê-los na hora, mas a tia o pegou… imaginei que minha tia fosse me repreender, mas de repente ela começa a se despir daquele jeito. Então ela disse: “Você está tão curioso? Você pode me tocar se quiser. Esta será uma aula especial.”  Alternative Titles: Banging My Aunt | Private x Lesson (XIX) | プライベート×レッスン | プライベート×レッスン (XIX) | 阿姨的家教課 | 음란과외",
  "artist": "HANSU",
  "author": "XIX",
  "cover": "https://awshc.r2d2storage.com/oldcovers/2022/04/obscene-private-lesson-cover.jpg",
  "chapters": {
    "003": {
      "title": "",
      "last_updated": "1783627798",
      "groups": {
        "XxTRUCOxX": "/proxy/api/imgchest/chapter/bp45vmp9vy5"
      }
    },
    "002": {
      "title": "",
      "last_updated": "1783627798",
      "groups": {
        "XxTRUCOxX": "/proxy/api/imgchest/chapter/a846n3w22yx"
      }
    },
    "004": {
      "title": "",
      "last_updated": "1783627799",
      "groups": {
        "XxTRUCOxX": "/proxy/api/imgchest/chapter/o24a92qbeyl"
      }
    },
    "001": {
      "title": "",
      "last_updated": "1783627802",
      "groups": {
        "XxTRUCOxX": "/proxy/api/imgchest/chapter/agyvpxqoky8"
      }
    },
    "005": {
      "title": "",
      "last_updated": "1783627808",
      "groups": {
        "XxTRUCOxX": "/proxy/api/imgchest/chapter/9249n2wq8yn"
      }
    },
    "006": {
      "title": "",
      "last_updated": "1783627810",
      "groups": {
        "XxTRUCOxX": "/proxy/api/imgchest/chapter/9p4novwb57n"
      }
    },
    "007": {
      "title": "",
      "last_updated": "1783627811",
      "groups": {
        "XxTRUCOxX": "/proxy/api/imgchest/chapter/ne7b9ldmgy5"
      }
    },
    "008": {
      "title": "",
      "last_updated": "1783627814",
      "groups": {
        "XxTRUCOxX": "/proxy/api/imgchest/chapter/dl7ppae2j7o"
      }
    },
    "009": {
      "title": "",
      "last_updated": "1783627820",
      "groups": {
        "XxTRUCOxX": "/proxy/api/imgchest/chapter/md7opawnlyp"
      }
    },
    "010": {
      "title": "",
      "last_updated": "1783627820",
      "groups": {
        "XxTRUCOxX": "/proxy/api/imgchest/chapter/na7kpam6w48"
      }
    },
    "011": {
      "title": "",
      "last_updated": "1783627822",
      "groups": {
        "XxTRUCOxX": "/proxy/api/imgchest/chapter/5xy25qa93yl"
      }
    },
    "012": {
      "title": "",
      "last_updated": "1783627826",
      "groups": {
        "XxTRUCOxX": "/proxy/api/imgchest/chapter/vj4jpeka948"
      }
    },
    "013": {
      "title": "",
      "last_updated": "1783627830",
      "groups": {
        "XxTRUCOxX": "/proxy/api/imgchest/chapter/ljyqpaxlx72"
      }
    },
    "014": {
      "title": "",
      "last_updated": "1783627831",
      "groups": {
        "XxTRUCOxX": "/proxy/api/imgchest/chapter/9ryd9qmw67k"
      }
    },
    "015": {
      "title": "",
      "last_updated": "1783627833",
      "groups": {
        "XxTRUCOxX": "/proxy/api/imgchest/chapter/6eyrka9jl7p"
      }
    },
    "016": {
      "title": "",
      "last_updated": "1783627837",
      "groups": {
        "XxTRUCOxX": "/proxy/api/imgchest/chapter/pg73adgnoyr"
      }
    },
    "017": {
      "title": "",
      "last_updated": "1783627839",
      "groups": {
        "XxTRUCOxX": "/proxy/api/imgchest/chapter/n87wp9d3q4x"
      }
    },
    "018": {
      "title": "",
      "last_updated": "1783627841",
      "groups": {
        "XxTRUCOxX": "/proxy/api/imgchest/chapter/lqyekd2ezyd"
      }
    },
    "019": {
      "title": "",
      "last_updated": "1783627845",
      "groups": {
        "XxTRUCOxX": "/proxy/api/imgchest/chapter/qb4z25ezl4j"
      }
    },
    "020": {
      "title": "",
      "last_updated": "1783627847",
      "groups": {
        "XxTRUCOxX": "/proxy/api/imgchest/chapter/qe4g9mjgkyj"
      }
    },
    "021": {
      "title": "",
      "last_updated": "1783627850",
      "groups": {
        "XxTRUCOxX": "/proxy/api/imgchest/chapter/bp45vmplvy5"
      }
    },
    "022": {
      "title": "",
      "last_updated": "1783627851",
      "groups": {
        "XxTRUCOxX": "/proxy/api/imgchest/chapter/o24a92qreyl"
      }
    },
    "023": {
      "title": "",
      "last_updated": "1783627855",
      "groups": {
        "XxTRUCOxX": "/proxy/api/imgchest/chapter/a846n3wj2yx"
      }
    },
    "024": {
      "title": "",
      "last_updated": "1783627857",
      "groups": {
        "XxTRUCOxX": "/proxy/api/imgchest/chapter/agyvpxqkky8"
      }
    },
    "026": {
      "title": "",
      "last_updated": "1783627862",
      "groups": {
        "XxTRUCOxX": "/proxy/api/imgchest/chapter/9249n2wr8yn"
      }
    },
    "025": {
      "title": "",
      "last_updated": "1783627862",
      "groups": {
        "XxTRUCOxX": "/proxy/api/imgchest/chapter/m9yxp9rw64q"
      }
    },
    "027": {
      "title": "",
      "last_updated": "1783627865",
      "groups": {
        "XxTRUCOxX": "/proxy/api/imgchest/chapter/9p4novw957n"
      }
    },
    "028": {
      "title": "",
      "last_updated": "1783627867",
      "groups": {
        "XxTRUCOxX": "/proxy/api/imgchest/chapter/ne7b9ldagy5"
      }
    },
    "030": {
      "title": "",
      "last_updated": "1783627871",
      "groups": {
        "XxTRUCOxX": "/proxy/api/imgchest/chapter/na7kpamjw48"
      }
    },
    "029": {
      "title": "",
      "last_updated": "1783627872",
      "groups": {
        "XxTRUCOxX": "/proxy/api/imgchest/chapter/md7opawmlyp"
      }
    },
    "031": {
      "title": "",
      "last_updated": "1783627875",
      "groups": {
        "XxTRUCOxX": "/proxy/api/imgchest/chapter/5xy25qak3yl"
      }
    },
    "032": {
      "title": "",
      "last_updated": "1783627877",
      "groups": {
        "XxTRUCOxX": "/proxy/api/imgchest/chapter/wl7lpagq3yx"
      }
    },
    "033": {
      "title": "",
      "last_updated": "1783627881",
      "groups": {
        "XxTRUCOxX": "/proxy/api/imgchest/chapter/vj4jpekl948"
      }
    },
    "034": {
      "title": "",
      "last_updated": "1783627881",
      "groups": {
        "XxTRUCOxX": "/proxy/api/imgchest/chapter/ljyqpaxwx72"
      }
    },
    "035": {
      "title": "",
      "last_updated": "1783627885",
      "groups": {
        "XxTRUCOxX": "/proxy/api/imgchest/chapter/9ryd9qmk67k"
      }
    },
    "036": {
      "title": "",
      "last_updated": "1783627886",
      "groups": {
        "XxTRUCOxX": "/proxy/api/imgchest/chapter/6eyrka9el7p"
      }
    },
    "038": {
      "title": "",
      "last_updated": "1783627890",
      "groups": {
        "XxTRUCOxX": "/proxy/api/imgchest/chapter/pg73adgeoyr"
      }
    },
    "037": {
      "title": "",
      "last_updated": "1783627890",
      "groups": {
        "XxTRUCOxX": "/proxy/api/imgchest/chapter/ej7mpawda7d"
      }
    },
    "039": {
      "title": "",
      "last_updated": "1783627894",
      "groups": {
        "XxTRUCOxX": "/proxy/api/imgchest/chapter/lqyekd2xzyd"
      }
    },
    "040": {
      "title": "",
      "last_updated": "1783627894",
      "groups": {
        "XxTRUCOxX": "/proxy/api/imgchest/chapter/qb4z25exl4j"
      }
    },
    "041": {
      "title": "",
      "last_updated": "1783627906",
      "groups": {
        "XxTRUCOxX": "/proxy/api/imgchest/chapter/qe4g9mjnkyj"
      }
    },
    "042": {
      "title": "",
      "last_updated": "1783627906",
      "groups": {
        "XxTRUCOxX": "/proxy/api/imgchest/chapter/xny8nevawyb"
      }
    },
    "044": {
      "title": "",
      "last_updated": "1783627908",
      "groups": {
        "XxTRUCOxX": "/proxy/api/imgchest/chapter/o24a92q5eyl"
      }
    },
    "043": {
      "title": "",
      "last_updated": "1783627911",
      "groups": {
        "XxTRUCOxX": "/proxy/api/imgchest/chapter/bp45vmpgvy5"
      }
    },
    "045": {
      "title": "",
      "last_updated": "1783627919",
      "groups": {
        "XxTRUCOxX": "/proxy/api/imgchest/chapter/agyvpxq5ky8"
      }
    },
    "046": {
      "title": "",
      "last_updated": "1783627922",
      "groups": {
        "XxTRUCOxX": "/proxy/api/imgchest/chapter/a846n3w82yx"
      }
    },
    "048": {
      "title": "",
      "last_updated": "1783627926",
      "groups": {
        "XxTRUCOxX": "/proxy/api/imgchest/chapter/9249n2w68yn"
      }
    },
    "047": {
      "title": "",
      "last_updated": "1783627926",
      "groups": {
        "XxTRUCOxX": "/proxy/api/imgchest/chapter/m9yxp9r664q"
      }
    },
    "049": {
      "title": "",
      "last_updated": "1783627936",
      "groups": {
        "XxTRUCOxX": "/proxy/api/imgchest/chapter/9p4novwr57n"
      }
    },
    "050": {
      "title": "",
      "last_updated": "1783627939",
      "groups": {
        "XxTRUCOxX": "/proxy/api/imgchest/chapter/ne7b9ldegy5"
      }
    },
    "051": {
      "title": "",
      "last_updated": "1783627939",
      "groups": {
        "XxTRUCOxX": "/proxy/api/imgchest/chapter/md7opaw2lyp"
      }
    },
    "052": {
      "title": "",
      "last_updated": "1783627942",
      "groups": {
        "XxTRUCOxX": "/proxy/api/imgchest/chapter/dl7ppaelj7o"
      }
    },
    "053": {
      "title": "",
      "last_updated": "1783627949",
      "groups": {
        "XxTRUCOxX": "/proxy/api/imgchest/chapter/na7kpam9w48"
      }
    },
    "054": {
      "title": "",
      "last_updated": "1783627950",
      "groups": {
        "XxTRUCOxX": "/proxy/api/imgchest/chapter/wl7lpagn3yx"
      }
    },
    "056": {
      "title": "",
      "last_updated": "1783627953",
      "groups": {
        "XxTRUCOxX": "/proxy/api/imgchest/chapter/ljyqpaxjx72"
      }
    },
    "055": {
      "title": "",
      "last_updated": "1783627956",
      "groups": {
        "XxTRUCOxX": "/proxy/api/imgchest/chapter/vj4jpekx948"
      }
    },
    "057": {
      "title": "",
      "last_updated": "1783627961",
      "groups": {
        "XxTRUCOxX": "/proxy/api/imgchest/chapter/vj4jpekxe48"
      }
    },
    "058": {
      "title": "",
      "last_updated": "1783627963",
      "groups": {
        "XxTRUCOxX": "/proxy/api/imgchest/chapter/ljyqpaxjk72"
      }
    },
    "059": {
      "title": "",
      "last_updated": "1783627964",
      "groups": {
        "XxTRUCOxX": "/proxy/api/imgchest/chapter/9ryd9qmgn7k"
      }
    },
    "060": {
      "title": "",
      "last_updated": "1783627966",
      "groups": {
        "XxTRUCOxX": "/proxy/api/imgchest/chapter/6eyrka9q67p"
      }
    },
    "062": {
      "title": "",
      "last_updated": "1783627973",
      "groups": {
        "XxTRUCOxX": "/proxy/api/imgchest/chapter/n87wp9dkb4x"
      }
    },
    "061": {
      "title": "",
      "last_updated": "1783627974",
      "groups": {
        "XxTRUCOxX": "/proxy/api/imgchest/chapter/ej7mpawbj7d"
      }
    },
    "063": {
      "title": "",
      "last_updated": "1783627974",
      "groups": {
        "XxTRUCOxX": "/proxy/api/imgchest/chapter/lqyekd28kyd"
      }
    },
    "064": {
      "title": "",
      "last_updated": "1783627979",
      "groups": {
        "XxTRUCOxX": "/proxy/api/imgchest/chapter/qb4z25egv4j"
      }
    },
    "067": {
      "title": "",
      "last_updated": "1783627983",
      "groups": {
        "XxTRUCOxX": "/proxy/api/imgchest/chapter/o24a92qwwyl"
      }
    },
    "066": {
      "title": "",
      "last_updated": "1783627985",
      "groups": {
        "XxTRUCOxX": "/proxy/api/imgchest/chapter/bp45vmpwgy5"
      }
    },
    "065": {
      "title": "",
      "last_updated": "1783627985",
      "groups": {
        "XxTRUCOxX": "/proxy/api/imgchest/chapter/xny8nevgdyb"
      }
    },
    "068": {
      "title": "",
      "last_updated": "1783627990",
      "groups": {
        "XxTRUCOxX": "/proxy/api/imgchest/chapter/a846n3wevyx"
      }
    },
    "069": {
      "title": "",
      "last_updated": "1783627997",
      "groups": {
        "XxTRUCOxX": "/proxy/api/imgchest/chapter/agyvpxqmzy8"
      }
    },
    "070": {
      "title": "",
      "last_updated": "1783628000",
      "groups": {
        "XxTRUCOxX": "/proxy/api/imgchest/chapter/ne7b9ld8vy5"
      }
    },
    "072": {
      "title": "",
      "last_updated": "1783628007",
      "groups": {
        "XxTRUCOxX": "/proxy/api/imgchest/chapter/dl7ppaexk7o"
      }
    },
    "073": {
      "title": "",
      "last_updated": "1783628013",
      "groups": {
        "XxTRUCOxX": "/proxy/api/imgchest/chapter/na7kpam3m48"
      }
    },
    "074": {
      "title": "",
      "last_updated": "1783628020",
      "groups": {
        "XxTRUCOxX": "/proxy/api/imgchest/chapter/md7opaw69yp"
      }
    },
    "076": {
      "title": "",
      "last_updated": "1783628021",
      "groups": {
        "XxTRUCOxX": "/proxy/api/imgchest/chapter/9ryd9qmvn7k"
      }
    },
    "075": {
      "title": "",
      "last_updated": "1783628022",
      "groups": {
        "XxTRUCOxX": "/proxy/api/imgchest/chapter/5xy25qaw8yl"
      }
    },
    "077": {
      "title": "",
      "last_updated": "1783628026",
      "groups": {
        "XxTRUCOxX": "/proxy/api/imgchest/chapter/n87wp9dwb4x"
      }
    },
    "078": {
      "title": "",
      "last_updated": "1783628034",
      "groups": {
        "XxTRUCOxX": "/proxy/api/imgchest/chapter/o24a92qzwyl"
      }
    },
    "079": {
      "title": "",
      "last_updated": "1783628036",
      "groups": {
        "XxTRUCOxX": "/proxy/api/imgchest/chapter/a846n3wvvyx"
      }
    },
    "084": {
      "title": "",
      "last_updated": "1783628043",
      "groups": {
        "XxTRUCOxX": "/proxy/api/imgchest/chapter/dl7ppadgk7o"
      }
    },
    "082": {
      "title": "",
      "last_updated": "1783628044",
      "groups": {
        "XxTRUCOxX": "/proxy/api/imgchest/chapter/9249n2pxayn"
      }
    },
    "085": {
      "title": "",
      "last_updated": "1783628059",
      "groups": {
        "XxTRUCOxX": "/proxy/api/imgchest/chapter/md7opaqz9yp"
      }
    },
    "088": {
      "title": "",
      "last_updated": "1783628059",
      "groups": {
        "XxTRUCOxX": "/proxy/api/imgchest/chapter/vj4jpegoe48"
      }
    },
    "087": {
      "title": "",
      "last_updated": "1783628059",
      "groups": {
        "XxTRUCOxX": "/proxy/api/imgchest/chapter/wl7lpa2zoyx"
      }
    },
    "086": {
      "title": "",
      "last_updated": "1783628060",
      "groups": {
        "XxTRUCOxX": "/proxy/api/imgchest/chapter/na7kpavxm48"
      }
    },
    "090": {
      "title": "",
      "last_updated": "1783628075",
      "groups": {
        "XxTRUCOxX": "/proxy/api/imgchest/chapter/6eyrkamr67p"
      }
    },
    "092": {
      "title": "",
      "last_updated": "1783628078",
      "groups": {
        "XxTRUCOxX": "/proxy/api/imgchest/chapter/ej7mpalzj7d"
      }
    },
    "093": {
      "title": "",
      "last_updated": "1783628078",
      "groups": {
        "XxTRUCOxX": "/proxy/api/imgchest/chapter/pg73ad5k3yr"
      }
    },
    "095": {
      "title": "",
      "last_updated": "1783628088",
      "groups": {
        "XxTRUCOxX": "/proxy/api/imgchest/chapter/lqyekdgjkyd"
      }
    },
    "096": {
      "title": "",
      "last_updated": "1783628092",
      "groups": {
        "XxTRUCOxX": "/proxy/api/imgchest/chapter/qb4z2586v4j"
      }
    },
    "098": {
      "title": "",
      "last_updated": "1783628095",
      "groups": {
        "XxTRUCOxX": "/proxy/api/imgchest/chapter/xny8ne5pdyb"
      }
    },
    "097": {
      "title": "",
      "last_updated": "1783628095",
      "groups": {
        "XxTRUCOxX": "/proxy/api/imgchest/chapter/qe4g9m5vbyj"
      }
    },
    "100": {
      "title": "",
      "last_updated": "1783628107",
      "groups": {
        "XxTRUCOxX": "/proxy/api/imgchest/chapter/a846n35rvyx"
      }
    },
    "102": {
      "title": "",
      "last_updated": "1783628108",
      "groups": {
        "XxTRUCOxX": "/proxy/api/imgchest/chapter/agyvpx9dzy8"
      }
    },
    "103": {
      "title": "",
      "last_updated": "1783628110",
      "groups": {
        "XxTRUCOxX": "/proxy/api/imgchest/chapter/m9yxp98kk4q"
      }
    },
    "105": {
      "title": "",
      "last_updated": "1783628113",
      "groups": {
        "XxTRUCOxX": "/proxy/api/imgchest/chapter/9249n2pzayn"
      }
    },
    "089": {
      "title": "",
      "last_updated": "1783630345",
      "groups": {
        "XxTRUCOxX": "/proxy/api/imgchest/chapter/ej7mpa82q7d"
      }
    },
    "080": {
      "title": "",
      "last_updated": "1783630346",
      "groups": {
        "XxTRUCOxX": "/proxy/api/imgchest/chapter/9ryd9qrpd7k"
      }
    },
    "083": {
      "title": "",
      "last_updated": "1783630346",
      "groups": {
        "XxTRUCOxX": "/proxy/api/imgchest/chapter/6eyrkaldk7p"
      }
    },
    "071": {
      "title": "",
      "last_updated": "1783630351",
      "groups": {
        "XxTRUCOxX": "/proxy/api/imgchest/chapter/ljyqpa2de72"
      }
    },
    "091": {
      "title": "",
      "last_updated": "1783630360",
      "groups": {
        "XxTRUCOxX": "/proxy/api/imgchest/chapter/n87wp9mr34x"
      }
    },
    "101": {
      "title": "",
      "last_updated": "1783630360",
      "groups": {
        "XxTRUCOxX": "/proxy/api/imgchest/chapter/qb4z25nkg4j"
      }
    },
    "099": {
      "title": "",
      "last_updated": "1783630364",
      "groups": {
        "XxTRUCOxX": "/proxy/api/imgchest/chapter/lqyekdmpxyd"
      }
    },
    "104": {
      "title": "",
      "last_updated": "1783630366",
      "groups": {
        "XxTRUCOxX": "/proxy/api/imgchest/chapter/qe4g9mwroyj"
      }
    },
    "094": {
      "title": "",
      "last_updated": "1783631498",
      "groups": {
        "XxTRUCOxX": "/proxy/api/imgchest/chapter/o24a92jj3yl"
      }
    },
    "081": {
      "title": "",
      "last_updated": "1783631499",
      "groups": {
        "XxTRUCOxX": "/proxy/api/imgchest/chapter/bp45vmqq2y5"
      }
    }
  }
}